<?xml version="1.0" encoding="UTF-8"?>
<metadata xml:lang="en"><Esri><CreaDate>20210309</CreaDate><CreaTime>13174700</CreaTime><ArcGISFormat>1.0</ArcGISFormat><SyncOnce>TRUE</SyncOnce><DataProperties><lineage><Process ToolSource="c:\program files (x86)\arcgis\desktop10.7\ArcToolbox\Toolboxes\Spatial Analyst Tools.tbx\ExtractValuesToPoints" Date="20210309" Time="131644">ExtractValuesToPoints Montney_grid SHmax_Ori F:\Afshin\GeoscienceBC\Stress\Shmax\Shapefile\SHmaxOri_MontGrid.shp NONE VALUE_ONLY</Process></lineage></DataProperties></Esri></metadata>
